padoru/__init__.py
padoru/main.py
padoru-0.1.1.dist-info/LICENSE
padoru-0.1.1.dist-info/METADATA
padoru-0.1.1.dist-info/WHEEL
padoru-0.1.1.dist-info/top_level.txt
padoru-0.1.1.dist-info/RECORD
