Metadata-Version: 2.1
Name: padoru
Version: 0.1.1
Summary: Hashire sori yo, kaze no you ni, tsukimihara wo, padoru padoru !
Author: BakaTaida
License: MIT
Classifier: Programming Language :: Python :: 3
Classifier: License :: OSI Approved :: MIT License
Classifier: Operating System :: OS Independent
Requires-Python: >=3.6
License-File: LICENSE
